{"note":"This file is an internal implementation detail to speed up HTML report generation. Its format can change at any time. You might be looking for the JSON report: https://coverage.rtfd.io/cmd.html#cmd-json","format":5,"version":"7.10.2","globals":"71f2e4c2dff5b58676f31730c0a29908","files":{"z_145eef247bfb46b6_Template_py":{"hash":"bd5540f26a379bafb275b2abea3fd1d2","index":{"url":"z_145eef247bfb46b6_Template_py.html","file":"src\\Template.py","description":"","nums":{"precision":0,"n_files":1,"n_statements":0,"n_excluded":0,"n_missing":0,"n_branches":0,"n_partial_branches":0,"n_missing_branches":0}}},"z_145eef247bfb46b6___init___py":{"hash":"e6baa73cda2916dad605215f937a92e1","index":{"url":"z_145eef247bfb46b6___init___py.html","file":"src\\__init__.py","description":"","nums":{"precision":0,"n_files":1,"n_statements":0,"n_excluded":0,"n_missing":0,"n_branches":0,"n_partial_branches":0,"n_missing_branches":0}}},"z_145eef247bfb46b6_category_py":{"hash":"fe7b0c823b47eaec07ba89e8dfba9424","index":{"url":"z_145eef247bfb46b6_category_py.html","file":"src\\category.py","description":"","nums":{"precision":0,"n_files":1,"n_statements":29,"n_excluded":0,"n_missing":0,"n_branches":0,"n_partial_branches":0,"n_missing_branches":0}}},"z_145eef247bfb46b6_product_py":{"hash":"cbc52c70848f7c5c48441b4d5534f842","index":{"url":"z_145eef247bfb46b6_product_py.html","file":"src\\product.py","description":"","nums":{"precision":0,"n_files":1,"n_statements":67,"n_excluded":0,"n_missing":3,"n_branches":0,"n_partial_branches":0,"n_missing_branches":0}}},"z_145eef247bfb46b6_utils_py":{"hash":"b5e65c778a6052c0793b42c79f97756d","index":{"url":"z_145eef247bfb46b6_utils_py.html","file":"src\\utils.py","description":"","nums":{"precision":0,"n_files":1,"n_statements":16,"n_excluded":0,"n_missing":0,"n_branches":0,"n_partial_branches":0,"n_missing_branches":0}}},"z_145eef247bfb46b6_product_in_category_iterator_py":{"hash":"721b2c05b01b4052c4e6a1ca0910461a","index":{"url":"z_145eef247bfb46b6_product_in_category_iterator_py.html","file":"src\\product_in_category_iterator.py","description":"","nums":{"precision":0,"n_files":1,"n_statements":13,"n_excluded":0,"n_missing":0,"n_branches":0,"n_partial_branches":0,"n_missing_branches":0}}},"z_145eef247bfb46b6_abstract_classes_py":{"hash":"c1135bd05bad8a52390f429d80fd0e8a","index":{"url":"z_145eef247bfb46b6_abstract_classes_py.html","file":"src\\abstract_classes.py","description":"","nums":{"precision":0,"n_files":1,"n_statements":20,"n_excluded":0,"n_missing":4,"n_branches":0,"n_partial_branches":0,"n_missing_branches":0}}},"z_145eef247bfb46b6_mixin_classes_py":{"hash":"a48587970d77cde8b20a768f80d61560","index":{"url":"z_145eef247bfb46b6_mixin_classes_py.html","file":"src\\mixin_classes.py","description":"","nums":{"precision":0,"n_files":1,"n_statements":5,"n_excluded":0,"n_missing":0,"n_branches":0,"n_partial_branches":0,"n_missing_branches":0}}},"z_145eef247bfb46b6_order_py":{"hash":"c14931000c615cb4408bc3a7de32cd76","index":{"url":"z_145eef247bfb46b6_order_py.html","file":"src\\order.py","description":"","nums":{"precision":0,"n_files":1,"n_statements":22,"n_excluded":0,"n_missing":1,"n_branches":0,"n_partial_branches":0,"n_missing_branches":0}}}}}